alpine_release_info/__init__.py
alpine_release_info/alpine.yml
alpine_release_info-1.0.0.dist-info/DESCRIPTION.rst
alpine_release_info-1.0.0.dist-info/METADATA
alpine_release_info-1.0.0.dist-info/RECORD
alpine_release_info-1.0.0.dist-info/WHEEL
alpine_release_info-1.0.0.dist-info/entry_points.txt
alpine_release_info-1.0.0.dist-info/metadata.json
alpine_release_info-1.0.0.dist-info/top_level.txt
