Metadata-Version: 2.0
Name: alpine-release-info
Version: 1.0.0
Summary: Alpine Linux release information
Home-page: https://github.com/privazio/alpine_release_info
Author: Rafael del Valle
Author-email: rvalle@valletech.eu
License: GPLv3
Keywords: linux alpine docker ansible puppet
Platform: UNKNOWN
Classifier: Development Status :: 4 - Beta
Classifier: Intended Audience :: Developers
Classifier: Topic :: Software Development :: Build Tools
Classifier: License :: OSI Approved :: MIT License
Classifier: Programming Language :: Python :: 2
Classifier: Programming Language :: Python :: 2.7
Requires-Dist: PyYAML
Requires-Dist: commandify
Provides-Extra: dev
Requires-Dist: check-manifest; extra == 'dev'
Provides-Extra: test
Requires-Dist: coverage; extra == 'test'
